muffnn/__init__.py
muffnn/core.py
muffnn/autoencoder/__init__.py
muffnn/autoencoder/autoencoder.py
muffnn/autoencoder/tests/__init__.py
muffnn/autoencoder/tests/test_autoencoder.py
muffnn/fm/__init__.py
muffnn/fm/fm_classifier.py
muffnn/fm/fm_regressor.py
muffnn/fm/tests/__init__.py
muffnn/fm/tests/test_fm_classifier.py
muffnn/fm/tests/test_fm_regressor.py
muffnn/fm/tests/util.py
muffnn/mlp/__init__.py
muffnn/mlp/base.py
muffnn/mlp/mlp_classifier.py
muffnn/mlp/mlp_regressor.py
muffnn/mlp/tests/__init__.py
muffnn/mlp/tests/test_base.py
muffnn/mlp/tests/test_mlp_classifier.py
muffnn/mlp/tests/test_mlp_regressor.py
muffnn/mlp/tests/util.py
muffnn/tests/__init__.py
muffnn/tests/test_tfbase.py
muffnn-2.3.2.dist-info/AUTHORS.md
muffnn-2.3.2.dist-info/LICENSE.txt
muffnn-2.3.2.dist-info/METADATA
muffnn-2.3.2.dist-info/WHEEL
muffnn-2.3.2.dist-info/top_level.txt
muffnn-2.3.2.dist-info/RECORD
