Metadata-Version: 2.1
Name: muffnn
Version: 2.3.2
Summary: Multilayer Feed-Forward Neural Network (MuFFNN) models with TensorFlow and scikit-learn
Home-page: https://github.com/civisanalytics/muffnn
Author: Civis Analytics, Inc.
Author-email: opensource@civisanalytics.com
License: BSD-3
Platform: UNKNOWN
Classifier: Programming Language :: Python
Classifier: Programming Language :: Python :: 3
Classifier: Programming Language :: Python :: 3.6
Classifier: Programming Language :: Python :: 3.7
Classifier: Programming Language :: Python :: 3 :: Only
Requires-Dist: numpy
Requires-Dist: scipy
Requires-Dist: scikit-learn (<0.23.0,>=0.20.0)
Requires-Dist: tensorflow (<2,>=1.15.4)
